cuaca/__init__.py
cuaca/api.py
cuaca-0.4.0.dist-info/LICENSE
cuaca-0.4.0.dist-info/WHEEL
cuaca-0.4.0.dist-info/METADATA
cuaca-0.4.0.dist-info/RECORD
