Metadata-Version: 2.1
Name: cuaca
Version: 0.4.0
Summary: A python wrapper for Malaysian Weather Service API
License: BSD-3-Clause
Author: sweemeng
Author-email: sweester@gmail.com
Requires-Python: >=3.8,<4.0
Classifier: License :: OSI Approved :: BSD License
Classifier: Programming Language :: Python :: 3
Classifier: Programming Language :: Python :: 3.10
Classifier: Programming Language :: Python :: 3.8
Classifier: Programming Language :: Python :: 3.9
Requires-Dist: requests (>=2.28.1,<3.0.0)
